Workbook

Sheet 📋 Premissas
A1: BRIF — Premissas do Modelo Financeiro | D1: Versão 1.0 · Abril 2025
A3: CUSTOS DE IA (OPENAI WHISPER + ANTHROPIC CLAUDE)
A4: Whisper — custo por minuto de áudio | B4: 0.006 | C4: USD/min · OpenAI Whisper API — large-v3. Fonte: openai.com/pricing
A5: Claude — custo por 1.000 tokens de entrada | B5: 0.003 | C5: USD/1k tok · claude-sonnet-4. Fonte: anthropic.com/pricing
A6: Claude — custo por 1.000 tokens de saída | B6: 0.015 | C6: USD/1k tok · claude-sonnet-4. Fonte: anthropic.com/pricing
A7: Taxa USD → BRL (câmbio referência) | B7: 5.2 | C7: BRL/USD · Atualizar conforme câmbio atual
A8: Tokens por reunião transcrita (entrada avg.) | B8: 4500 | C8: tokens · ~90 min de áudio → ~4.500 tokens de transcrição para briefing
A9: Tokens por briefing gerado (saída avg.) | B9: 1200 | C9: tokens · Briefing consolidado estruturado — estimativa
A10: Tokens por proposta HTML gerada (saída avg.) | B10: 3500 | C10: tokens · Proposta visual completa — estimativa
A13: PLANOS — LIMITES E PREÇOS (INPUTS EDITÁVEIS)
B14: Basic | C14: Pro | D14: Observação
A15: Usuários internos (limite) | B15: 5 | C15: 20
A16: Projetos ativos simultâneos (limite) | B16: 5 | C16: 30
A17: Transcrições — minutos inclusos/mês | B17: 120 | C17: 600 | D17: Limite de Whisper por plano
A18: Propostas IA — quantidade incluída/mês | B18: 10 | C18: 50 | D18: Chamadas Claude para proposta
A19: Storage incluído — GB | B19: 5 | C19: 50 | D19: Cloudflare R2
A20: Preço mensal — R$ | B20: 297 | C20: 697 | D20: Receita bruta por tenant/mês
A23: CUSTOS DE INFRAESTRUTURA FIXOS/MÊS (BRL)
A24: Vercel Pro (frontend) | B24: 300 | C24: Vercel.com — plano Pro ~$20/mês
A25: Railway (backend + Redis) | B25: 500 | C25: Railway.app — estimativa para MVP
A26: Cloudflare Workers + R2 | B26: 150 | C26: DNS, SSL, storage — estimativa base
A27: Resend (e-mail transacional) | B27: 100 | C27: Resend.com — plano escalonável
A28: Stripe (billing) — % sobre receita | B28: 0 | C28: Ver aba Projeção: cobrado como % da receita
A29: Domínio + certificados | B29: 80 | C29: Registro.br + extras
A30: Monitoramento (Sentry/Datadog) | B30: 200 | C30: Estimativa inicial
A32: ℹ Células em AZUL são inputs editáveis. Células em PRETO são calculadas pelas fórmulas.

Sheet 💰 Custo por Tenant
A1: Custo de IA por Tenant — Cenários de Uso
A3: PREMISSAS DE USO — CENÁRIOS (editável)
A4: Parâmetro de Uso | B4: Baixo (conservador) | C4: Médio (esperado) | D4: Alto (intenso) | F4: Fonte / Nota
A5: Reuniões de briefing por mês (por tenant) | B5: 3 | C5: 6 | D5: 12
A6: Duração média de reunião (minutos) | B6: 45 | C6: 60 | D6: 90
A7: Propostas visuais geradas por mês | B7: 3 | C7: 6 | D7: 12
A8: Taxa de debriefing (% de projetos com ajuste) | B8: 0.3 | C8: 0.5 | D8: 0.7 | F8: Percentual de projetos que geram debriefing
A10: CUSTO MENSAL DE IA POR TENANT (R$) — CALCULADO
A11: Item de Custo | B11: Cenário Baixo | C11: Cenário Médio | D11: Cenário Alto | F11: Fórmula / Lógica
A12: Minutos de áudio transcrito/mês | B12: =B5*B6 -> 135 | C12: =C5*C6 -> 360 | D12: =D5*D6 -> 1080 | F12: reuniões × duração média
A13: Custo Whisper — USD | B13: ='📋 Premissas'!B4*B12 -> 0.81 | C13: ='📋 Premissas'!B4*C12 -> 2.16 | D13: ='📋 Premissas'!B4*D12 -> 6.48 | F13: custo/min × minutos totais
A14: Custo Whisper — BRL | B14: =B13*'📋 Premissas'!B7 -> 4.212 | C14: =C13*'📋 Premissas'!B7 -> 11.232 | D14: =D13*'📋 Premissas'!B7 -> 33.696 | F14: USD × câmbio
A15: Tokens Claude entrada/mês (briefings + debriefings) | B15: =B5*(1+B8)*'📋 Premissas'!B8 -> 17550 | C15: =C5*(1+C8)*'📋 Premissas'!B8 -> 40500 | D15: =D5*(1+D8)*'📋 Premissas'!B8 -> 91800 | F15: reuniões × (1+taxa_debriefing) × tokens/reunião
A16: Custo Claude entrada — BRL | B16: =B15/1000*'📋 Premissas'!B5*'📋 Premissas'!B7 -> 0.27378 | C16: =C15/1000*'📋 Premissas'!B5*'📋 Premissas'!B7 -> 0.6318 | D16: =D15/1000*'📋 Premissas'!B5*'📋 Premissas'!B7 -> 1.43208 | F16: tokens/1000 × custo_1k × câmbio
A17: Tokens Claude saída/mês (briefings) | B17: =B5*(1+B8)*'📋 Premissas'!B9 -> 4680 | C17: =C5*(1+C8)*'📋 Premissas'!B9 -> 10800 | D17: =D5*(1+D8)*'📋 Premissas'!B9 -> 24480 | F17: reuniões × (1+debriefing) × tokens saída briefing
A18: Tokens Claude saída/mês (propostas) | B18: =B7*'📋 Premissas'!B10 -> 10500 | C18: =C7*'📋 Premissas'!B10 -> 21000 | D18: =D7*'📋 Premissas'!B10 -> 42000 | F18: propostas × tokens por proposta
A19: Custo Claude saída — BRL | B19: =(B17+B18)/1000*'📋 Premissas'!B6*'📋 Premissas'!B7 -> 1.18404 | C19: =(C17+C18)/1000*'📋 Premissas'!B6*'📋 Premissas'!B7 -> 2.4804 | D19: =(D17+D18)/1000*'📋 Premissas'!B6*'📋 Premissas'!B7 -> 5.18544 | F19: (tok_briefing + tok_proposta)/1000 × custo × câmbio
A20: CUSTO TOTAL IA/MÊS — R$ | B20: =B14+B16+B19 -> 5.66982 | C20: =C14+C16+C19 -> 14.3442 | D20: =D14+D16+D19 -> 40.31352 | F20: Whisper BRL + Claude entrada BRL + Claude saída BRL
A23: MARGEM BRUTA POR PLANO — APÓS CUSTO DE IA (R$/mês por tenant)
A24: Cenário de Uso | B24: Receita Basic | C24: Custo IA | D24: Margem Basic | E24: Receita Pro | F24: Margem Pro
A25: Cenário Baixo | B25: ='📋 Premissas'!B20 -> 297 | C25: =B22 -> 0 | D25: =B25-C25 -> 297 | E25: ='📋 Premissas'!C20 -> 697 | F25: =E25-C25 -> 697
A26: Cenário Médio | B26: ='📋 Premissas'!B20 -> 297 | C26: =C22 -> 0 | D26: =B26-C26 -> 297 | E26: ='📋 Premissas'!C20 -> 697 | F26: =E26-C26 -> 697
A27: Cenário Alto | B27: ='📋 Premissas'!B20 -> 297 | C27: =D22 -> 0 | D27: =B27-C27 -> 297 | E27: ='📋 Premissas'!C20 -> 697 | F27: =E27-C27 -> 697
A28: % CUSTO DE IA SOBRE RECEITA — META: ABAIXO DE 15%
A29: Cenário | B29: Basic | E29: Pro
A30: Cenário Baixo | B30: =C25/B25 -> 0 | C30: ← OK se < 15% | E30: =C25/E25 -> 0 | F30: ← OK se < 15%
A31: Cenário Médio | B31: =C26/B26 -> 0 | C31: ← OK se < 15% | E31: =C26/E26 -> 0 | F31: ← OK se < 15%
A32: Cenário Alto | B32: =C27/B27 -> 0 | C32: ← OK se < 15% | E32: =C27/E27 -> 0 | F32: ← OK se < 15%

Sheet 📈 Projeção 12 Meses
A1: BRIF — Projeção de Receita e Custos · 12 Meses
A3: CRESCIMENTO DE TENANTS POR MÊS (editável — azul)
A4: Métrica | B4: M1 | C4: M2 | D4: M3 | E4: M4 | F4: M5 | G4: M6 | H4: M7 | I4: M8 | J4: M9 | K4: M10 | L4: M11 | M4: M12
A5: Novos tenants Basic | B5: 0 | C5: 0 | D5: 0 | E5: 0 | F5: 1 | G5: 1 | H5: 1 | I5: 2 | J5: 2 | K5: 2 | L5: 3 | M5: 3
A6: Novos tenants Pro | B6: 0 | C6: 0 | D6: 0 | E6: 0 | F6: 0 | G6: 1 | H6: 1 | I6: 1 | J6: 1 | K6: 2 | L6: 2 | M6: 2
A7: Churn tenants/mês | B7: 0 | C7: 0 | D7: 0 | E7: 0 | F7: 0 | G7: 0 | H7: 0 | I7: 0 | J7: 1 | K7: 1 | L7: 1 | M7: 1
A8: Tenants Basic acum. | B8: =B5+B6-B7 -> 0 | C8: =B8+C5-C7 -> 0 | D8: =C8+D5-D7 -> 0 | E8: =D8+E5-E7 -> 0 | F8: =E8+F5-F7 -> 1 | G8: =F8+G5-G7 -> 2 | H8: =G8+H5-H7 -> 3 | I8: =H8+I5-I7 -> 5 | J8: =I8+J5-J7 -> 6 | ... M8: =L8+M5-M7 -> 11
A9: Tenants Pro acum. | B9: =B6 -> 0 | C9: =B9+C6 -> 0 | D9: =C9+D6 -> 0 | E9: =D9+E6 -> 0 | F9: =E9+F6 -> 0 | G9: =F9+G6 -> 1 | H9: =G9+H6 -> 2 | I9: =H9+I6 -> 3 | J9: =I9+J6 -> 4 | ... M9: =L9+M6 -> 10
A10: Total tenants pagantes | B10: =B8+B9 -> 0 | C10: =C8+C9 -> 0 | D10: =D8+D9 -> 0 | E10: =E8+E9 -> 0 | F10: =F8+F9 -> 1 | G10: =G8+G9 -> 3 | H10: =H8+H9 -> 5 | I10: =I8+I9 -> 8 | ... M10: =M8+M9 -> 21
A12: RECEITA MENSAL (R$)
A13: Receita Basic | B13: =B8*'📋 Premissas'!B20 -> 0 | C13: =C8*'📋 Premissas'!B20 -> 0 | D13: =D8*'📋 Premissas'!B20 -> 0 | E13: =E8*'📋 Premissas'!B20 -> 0 | F13: =F8*'📋 Premissas'!B20 -> 297 | G13: =G8*'📋 Premissas'!B20 -> 594 | H13: =H8*'📋 Premissas'!B20 -> 891 | I13: =I8*'📋 Premissas'!B20 -> 1485 | J13: =J8*'📋 Premissas'!B20 -> 1782 | K13: =K8*'📋 Premissas'!B20 -> 2079 | L13: =L8*'📋 Premissas'!B20 -> 2673 | M13: =M8*'📋 Premissas'!B20 -> 3267
A14: Receita Pro | B14: =B9*'📋 Premissas'!C20 -> 0 | C14: =C9*'📋 Premissas'!C20 -> 0 | D14: =D9*'📋 Premissas'!C20 -> 0 | E14: =E9*'📋 Premissas'!C20 -> 0 | F14: =F9*'📋 Premissas'!C20 -> 0 | G14: =G9*'📋 Premissas'!C20 -> 697 | H14: =H9*'📋 Premissas'!C20 -> 1394 | I14: =I9*'📋 Premissas'!C20 -> 2091 | J14: =J9*'📋 Premissas'!C20 -> 2788 | K14: =K9*'📋 Premissas'!C20 -> 4182 | L14: =L9*'📋 Premissas'!C20 -> 5576 | M14: =M9*'📋 Premissas'!C20 -> 6970
A15: Receita Total (MRR) | B15: =B13+B14 -> 0 | C15: =C13+C14 -> 0 | D15: =D13+D14 -> 0 | E15: =E13+E14 -> 0 | F15: =F13+F14 -> 297 | G15: =G13+G14 -> 1291 | H15: =H13+H14 -> 2285 | I15: =I13+I14 -> 3576 | ... M15: =M13+M14 -> 10237
A17: CUSTOS MENSAIS (R$)
A18: Custo IA — tenants Basic (cenário médio) | B18: =B9*'💰 Custo por Tenant'!C20 -> 0 | C18: =C9*'💰 Custo por Tenant'!C20 -> 0 | D18: =D9*'💰 Custo por Tenant'!C20 -> 0 | E18: =E9*'💰 Custo por Tenant'!C20 -> 0 | F18: =F9*'💰 Custo por Tenant'!C20 -> 0 | G18: =G9*'💰 Custo por Tenant'!C20 -> 14.3442 | H18: =H9*'💰 Custo por Tenant'!C20 -> 28.6884 | I18: =I9*'💰 Custo por Tenant'!C20 -> 43.0326 | J18: =J9*'💰 Custo por Tenant'!C20 -> 57.3768 | K18: =K9*'💰 Custo por Tenant'!C20 -> 86.0652 | L18: =L9*'💰 Custo por Tenant'!C20 -> 114.7536 | M18: =M9*'💰 Custo por Tenant'!C20 -> 143.442
A19: Custo IA — tenants Pro (cenário médio) | B19: =B10*'💰 Custo por Tenant'!C20 -> 0 | C19: =C10*'💰 Custo por Tenant'!C20 -> 0 | D19: =D10*'💰 Custo por Tenant'!C20 -> 0 | E19: =E10*'💰 Custo por Tenant'!C20 -> 0 | F19: =F10*'💰 Custo por Tenant'!C20 -> 14.3442 | G19: =G10*'💰 Custo por Tenant'!C20 -> 43.0326 | H19: =H10*'💰 Custo por Tenant'!C20 -> 71.721 | I19: =I10*'💰 Custo por Tenant'!C20 -> 114.7536 | J19: =J10*'💰 Custo por Tenant'!C20 -> 143.442 | K19: =K10*'💰 Custo por Tenant'!C20 -> 186.4746 | L19: =L10*'💰 Custo por Tenant'!C20 -> 243.8514 | M19: =M10*'💰 Custo por Tenant'!C20 -> 301.2282
A20: Custo Stripe (1,4% da receita) | B20: =B15*0.014 -> 0 | C20: =C15*0.014 -> 0 | D20: =D15*0.014 -> 0 | E20: =E15*0.014 -> 0 | F20: =F15*0.014 -> 4.158 | G20: =G15*0.014 -> 18.074 | H20: =H15*0.014 -> 31.99 | I20: =I15*0.014 -> 50.064 | ... M20: =M15*0.014 -> 143.318
A21: Infraestrutura fixa | B21: =SUM('📋 Premissas'!B24:B30) -> 1330 | C21: =SUM('📋 Premissas'!B24:B30) -> 1330 | D21: =SUM('📋 Premissas'!B24:B30) -> 1330 | E21: =SUM('📋 Premissas'!B24:B30) -> 1330 | F21: =SUM('📋 Premissas'!B24:B30) -> 1330 | G21: =SUM('📋 Premissas'!B24:B30) -> 1330 | H21: =SUM('📋 Premissas'!B24:B30) -> 1330 | I21: =SUM('📋 Premissas'!B24:B30) -> 1330 | J21: =SUM('📋 Premissas'!B24:B30) -> 1330 | K21: =SUM('📋 Premissas'!B24:B30) -> 1330 | L21: =SUM('📋 Premissas'!B24:B30) -> 1330 | M21: =SUM('📋 Premissas'!B24:B30) -> 1330
A22: CUSTO TOTAL | B22: =SUM(B18:B21) -> 1330 | C22: =SUM(C18:C21) -> 1330 | D22: =SUM(D18:D21) -> 1330 | E22: =SUM(E18:E21) -> 1330 | F22: =SUM(F18:F21) -> 1348.5022 | G22: =SUM(G18:G21) -> 1405.4508 | H22: =SUM(H18:H21) -> 1462.3994 | I22: =SUM(I18:I21) -> 1537.8502 | ... M22: =SUM(M18:M21) -> 1917.9882
A25: RESULTADO OPERACIONAL (R$)
A26: Receita Total | B26: =B15 -> 0 | C26: =C15 -> 0 | D26: =D15 -> 0 | E26: =E15 -> 0 | F26: =F15 -> 297 | G26: =G15 -> 1291 | H26: =H15 -> 2285 | I26: =I15 -> 3576 | ... M26: =M15 -> 10237
A27: Custo Total | B27: =B23 -> 0 | C27: =C23 -> 0 | D27: =D23 -> 0 | E27: =E23 -> 0 | F27: =F23 -> 0 | G27: =G23 -> 0 | H27: =H23 -> 0 | I27: =I23 -> 0 | ... M27: =M23 -> 0
A28: Resultado Líquido | B28: =B26-B27 -> 0 | C28: =C26-C27 -> 0 | D28: =D26-D27 -> 0 | E28: =E26-E27 -> 0 | F28: =F26-F27 -> 297 | G28: =G26-G27 -> 1291 | H28: =H26-H27 -> 2285 | I28: =I26-I27 -> 3576 | ... M28: =M26-M27 -> 10237
A29: Margem Operacional (%) | B29: =IFERROR(B28/B26,0) -> 0 | C29: =IFERROR(C28/C26,0) -> 0 | D29: =IFERROR(D28/D26,0) -> 0 | E29: =IFERROR(E28/E26,0) -> 0 | F29: =IFERROR(F28/F26,0) -> 1 | G29: =IFERROR(G28/G26,0) -> 1 | H29: =IFERROR(H28/H26,0) -> 1 | I29: =IFERROR(I28/I26,0) -> 1 | ... M29: =IFERROR(M28/M26,0) -> 1

Sheet 🎯 Resumo Executivo
A1: BRIF — Resumo Executivo de Viabilidade
A3: INDICADORES-CHAVE DE VIABILIDADE
A4: Indicador | B4: Valor Calculado | C4: Referência | D4: Interpretação
A5: 🟢 Break-even de IA (Basic / Médio) | B5: ='💰 Custo por Tenant'!C26 -> 0 | C5: ='💰 Custo por Tenant'!B26 -> 297 | D5: Custo IA vs Receita Basic no cenário médio de uso
A6: 🟡 % Custo IA sobre receita (Basic / Médio) | B6: ='💰 Custo por Tenant'!C31 -> ← OK se < 15% | C6: Meta: < 15% | D6: Se > 15%, ajustar limites do plano ou preço
A7: 🟡 % Custo IA sobre receita (Pro / Médio) | B7: ='💰 Custo por Tenant'!E31 -> 0 | C7: Meta: < 12% | D7: Pro tem mais uso — monitorar de perto
A8: 📊 MRR projetado mês 6 | B8: ='📈 Projeção 12 Meses'!G15 -> 1291 | C8: Meta: R$ 5.000 | D8: Validar se mix de planos alcança a meta
A9: 📊 MRR projetado mês 12 | B9: ='📈 Projeção 12 Meses'!N15 -> 0 | C9: Meta: R$ 30.000 | D9: Depende da aceleração de vendas em M7+
A10: 💡 Custo infra fixa/mês | B10: =SUM('📋 Premissas'!B24:B30) -> 1330 | C10: Fixo independente de tenants | D10: Revisar mensalmente conforme escala
A13: RECOMENDAÇÕES ANTES DO LANÇAMENTO
A14: # | B14: Ação | C14: Detalhe
A15: 1 | B15: Validar custo real de IA | C15: Rodar 10 briefings reais durante o dogfooding e comparar com as estimativas desta planilha. Ajustar premissas se necessário.
A16: 2 | B16: Calibrar limites dos planos | C16: Se o custo de IA > 15% da receita no cenário médio, reduzir minutos inclusos no Basic ou aumentar o preço.
A17: 3 | B17: Definir câmbio de referência | C17: O custo de Whisper e Claude é em USD. Com câmbio volátil, considerar hedge ou reajuste semestral de preços.
A18: 4 | B18: Monitorar custo/tenant no admin | C18: O painel Super Admin deve exibir custo de IA acumulado por tenant em tempo real para identificar abusos.
A19: 5 | B19: Simular cenário de 50 tenants | C19: Com 50 tenants no mix 60%/40% (Basic/Pro) e uso médio, o modelo deve ser positivo. Usar a aba de Projeção.
A20: 6 | B20: Validar preços com mercado | C20: R$297 e R$697 são referências. Realizar 5 conversas de vendas antes do lançamento para testar elasticidade.
